pybry/LBRYException.py
pybry/__init__.py
pybry/__lbryd_api__.py
pybry/_generator.py
pybry/base_api.py
pybry/constants.py
pybry/lbrycrd_api.py
pybry/lbryd_api.py
pybry/lbryd_api_test.py
pybry/test.py
pybry-1.6.4.dist-info/LICENSE
pybry-1.6.4.dist-info/METADATA
pybry-1.6.4.dist-info/WHEEL
pybry-1.6.4.dist-info/top_level.txt
pybry-1.6.4.dist-info/RECORD
