Metadata-Version: 2.1
Name: pybry
Version: 1.6.4
Summary: A Binded Python API for the LBRYD and LBRYCRD network
Home-page: https://github.com/osilkin98/pybry
Author: Oleg Silkin
Author-email: o.silkin98@gmail.com
License: MIT License
Platform: UNKNOWN
Requires: yapf
Requires-Python: >=3
